[
  {
    "TokenId": "SCZ-GVB-0001",
    "TokenType": "GovernmentBond",
    "Name": "SCZ Custody \u2013 GoZ Bond 2023-01",
    "Description": "Government of Zambia bond in Standard Chartered custody. Maturity: 2026. Coupon: 6.0%",
    "OwnerDid": "did:zambia:bank:scz-001",
    "OwnerName": "Standard Chartered Zambia",
    "Status": "Active",
    "Value": 30019270.72,
    "Currency": "ZMW",
    "Quantity": 21726,
    "CreatedAt": "2023-07-11T05:21:22",
    "Province": "Lusaka",
    "District": "Lusaka",
    "IsFractionalized": true,
    "IsLocked": false
  },
  {
    "TokenId": "SCZ-GVB-0002",
    "TokenType": "GovernmentBond",
    "Name": "SCZ Custody \u2013 GoZ Bond 2023-02",
    "Description": "Government of Zambia bond in Standard Chartered custody. Maturity: 2026. Coupon: 6.0%",
    "OwnerDid": "did:zambia:bank:scz-001",
    "OwnerName": "Standard Chartered Zambia",
    "Status": "Active",
    "Value": 36003137.43,
    "Currency": "ZMW",
    "Quantity": 10955,
    "CreatedAt": "2025-01-09T05:21:22",
    "Province": "Lusaka",
    "District": "Lusaka",
    "IsFractionalized": true,
    "IsLocked": false
  },
  {
    "TokenId": "SCZ-GVB-0003",
    "TokenType": "GovernmentBond",
    "Name": "SCZ Custody \u2013 GoZ Bond 2023-03",
    "Description": "Government of Zambia bond in Standard Chartered custody. Maturity: 2027. Coupon: 6.0%",
    "OwnerDid": "did:zambia:bank:scz-001",
    "OwnerName": "Standard Chartered Zambia",
    "Status": "Active",
    "Value": 19549463.43,
    "Currency": "ZMW",
    "Quantity": 5565,
    "CreatedAt": "2024-09-30T05:21:22",
    "Province": "Lusaka",
    "District": "Lusaka",
    "IsFractionalized": true,
    "IsLocked": false
  },
  {
    "TokenId": "SCZ-GVB-0004",
    "TokenType": "GovernmentBond",
    "Name": "SCZ Custody \u2013 GoZ Bond 2023-04",
    "Description": "Government of Zambia bond in Standard Chartered custody. Maturity: 2027. Coupon: 7.0%",
    "OwnerDid": "did:zambia:bank:scz-001",
    "OwnerName": "Standard Chartered Zambia",
    "Status": "Active",
    "Value": 17962081.41,
    "Currency": "ZMW",
    "Quantity": 17146,
    "CreatedAt": "2025-02-23T05:21:22",
    "Province": "Lusaka",
    "District": "Lusaka",
    "IsFractionalized": true,
    "IsLocked": false
  },
  {
    "TokenId": "SCZ-GVB-0005",
    "TokenType": "GovernmentBond",
    "Name": "SCZ Custody \u2013 GoZ Bond 2024-05",
    "Description": "Government of Zambia bond in Standard Chartered custody. Maturity: 2027. Coupon: 7.0%",
    "OwnerDid": "did:zambia:bank:scz-001",
    "OwnerName": "Standard Chartered Zambia",
    "Status": "Active",
    "Value": 12080573.05,
    "Currency": "ZMW",
    "Quantity": 9383,
    "CreatedAt": "2025-07-27T05:21:22",
    "Province": "Lusaka",
    "District": "Lusaka",
    "IsFractionalized": true,
    "IsLocked": false
  },
  {
    "TokenId": "SCZ-GVB-0006",
    "TokenType": "GovernmentBond",
    "Name": "SCZ Custody \u2013 GoZ Bond 2024-06",
    "Description": "Government of Zambia bond in Standard Chartered custody. Maturity: 2028. Coupon: 7.0%",
    "OwnerDid": "did:zambia:bank:scz-001",
    "OwnerName": "Standard Chartered Zambia",
    "Status": "Active",
    "Value": 34033651.8,
    "Currency": "ZMW",
    "Quantity": 27374,
    "CreatedAt": "2024-12-02T05:21:22",
    "Province": "Lusaka",
    "District": "Lusaka",
    "IsFractionalized": true,
    "IsLocked": false
  },
  {
    "TokenId": "SCZ-GVB-0007",
    "TokenType": "GovernmentBond",
    "Name": "SCZ Custody \u2013 GoZ Bond 2024-07",
    "Description": "Government of Zambia bond in Standard Chartered custody. Maturity: 2028. Coupon: 7.0%",
    "OwnerDid": "did:zambia:bank:scz-001",
    "OwnerName": "Standard Chartered Zambia",
    "Status": "Active",
    "Value": 26052082.69,
    "Currency": "ZMW",
    "Quantity": 15498,
    "CreatedAt": "2023-09-05T05:21:22",
    "Province": "Lusaka",
    "District": "Lusaka",
    "IsFractionalized": true,
    "IsLocked": false
  },
  {
    "TokenId": "SCZ-GVB-0008",
    "TokenType": "GovernmentBond",
    "Name": "SCZ Custody \u2013 GoZ Bond 2024-08",
    "Description": "Government of Zambia bond in Standard Chartered custody. Maturity: 2028. Coupon: 8.0%",
    "OwnerDid": "did:zambia:bank:scz-001",
    "OwnerName": "Standard Chartered Zambia",
    "Status": "Active",
    "Value": 20085128.67,
    "Currency": "ZMW",
    "Quantity": 19213,
    "CreatedAt": "2025-12-28T05:21:22",
    "Province": "Lusaka",
    "District": "Lusaka",
    "IsFractionalized": true,
    "IsLocked": false
  },
  {
    "TokenId": "SCZ-CRB-0009",
    "TokenType": "CorporateBond",
    "Name": "Zambia Breweries Corporate Bond 2023-09",
    "Description": "Fixed-rate corporate bond issued by Zambia Breweries. Tenor: 5 years. Coupon: 10.0%",
    "OwnerDid": "did:zambia:bank:scz-001",
    "OwnerName": "Standard Chartered Zambia",
    "Status": "Active",
    "Value": 3476088.98,
    "Currency": "ZMW",
    "Quantity": 4092,
    "CreatedAt": "2024-06-22T05:21:22",
    "Province": "Lusaka",
    "District": "Lusaka",
    "IsFractionalized": true,
    "IsLocked": false,
    "LockedReason": null
  },
  {
    "TokenId": "SCZ-CRB-0010",
    "TokenType": "CorporateBond",
    "Name": "ZESCO Corporate Bond 2023-10",
    "Description": "Fixed-rate corporate bond issued by ZESCO. Tenor: 5 years. Coupon: 11.0%",
    "OwnerDid": "did:zambia:bank:scz-001",
    "OwnerName": "Standard Chartered Zambia",
    "Status": "Locked",
    "Value": 1005362.56,
    "Currency": "ZMW",
    "Quantity": 3223,
    "CreatedAt": "2024-06-21T05:21:22",
    "Province": "Lusaka",
    "District": "Lusaka",
    "IsFractionalized": true,
    "IsLocked": true,
    "LockedReason": "Pledged as repo collateral"
  },
  {
    "TokenId": "SCZ-CRB-0011",
    "TokenType": "CorporateBond",
    "Name": "ZAMTEL Corporate Bond 2023-11",
    "Description": "Fixed-rate corporate bond issued by ZAMTEL. Tenor: 5 years. Coupon: 11.0%",
    "OwnerDid": "did:zambia:bank:scz-001",
    "OwnerName": "Standard Chartered Zambia",
    "Status": "Active",
    "Value": 1100450.49,
    "Currency": "ZMW",
    "Quantity": 508,
    "CreatedAt": "2025-08-03T05:21:22",
    "Province": "Lusaka",
    "District": "Lusaka",
    "IsFractionalized": true,
    "IsLocked": false,
    "LockedReason": null
  },
  {
    "TokenId": "SCZ-CRB-0012",
    "TokenType": "CorporateBond",
    "Name": "Chilanga Cement Corporate Bond 2024-12",
    "Description": "Fixed-rate corporate bond issued by Chilanga Cement. Tenor: 6 years. Coupon: 11.0%",
    "OwnerDid": "did:zambia:bank:scz-001",
    "OwnerName": "Standard Chartered Zambia",
    "Status": "Active",
    "Value": 5375052.8,
    "Currency": "ZMW",
    "Quantity": 6062,
    "CreatedAt": "2024-08-18T05:21:22",
    "Province": "Lusaka",
    "District": "Lusaka",
    "IsFractionalized": true,
    "IsLocked": false,
    "LockedReason": null
  },
  {
    "TokenId": "SCZ-CRB-0013",
    "TokenType": "CorporateBond",
    "Name": "Madison Insurance Corporate Bond 2024-13",
    "Description": "Fixed-rate corporate bond issued by Madison Insurance. Tenor: 6 years. Coupon: 11.0%",
    "OwnerDid": "did:zambia:bank:scz-001",
    "OwnerName": "Standard Chartered Zambia",
    "Status": "Active",
    "Value": 3818113.54,
    "Currency": "ZMW",
    "Quantity": 1694,
    "CreatedAt": "2026-01-13T05:21:22",
    "Province": "Lusaka",
    "District": "Lusaka",
    "IsFractionalized": true,
    "IsLocked": false,
    "LockedReason": null
  },
  {
    "TokenId": "SCZ-CRB-0014",
    "TokenType": "CorporateBond",
    "Name": "ZSIC Life Corporate Bond 2024-14",
    "Description": "Fixed-rate corporate bond issued by ZSIC Life. Tenor: 6 years. Coupon: 11.0%",
    "OwnerDid": "did:zambia:bank:scz-001",
    "OwnerName": "Standard Chartered Zambia",
    "Status": "Active",
    "Value": 5518496.24,
    "Currency": "ZMW",
    "Quantity": 5362,
    "CreatedAt": "2024-10-09T05:21:22",
    "Province": "Lusaka",
    "District": "Lusaka",
    "IsFractionalized": true,
    "IsLocked": false,
    "LockedReason": null
  },
  {
    "TokenId": "SCZ-CRB-0015",
    "TokenType": "CorporateBond",
    "Name": "Atlas Mara Corporate Bond 2024-15",
    "Description": "Fixed-rate corporate bond issued by Atlas Mara. Tenor: 6 years. Coupon: 12.0%",
    "OwnerDid": "did:zambia:bank:scz-001",
    "OwnerName": "Standard Chartered Zambia",
    "Status": "Locked",
    "Value": 9990251.99,
    "Currency": "ZMW",
    "Quantity": 3114,
    "CreatedAt": "2024-04-27T05:21:22",
    "Province": "Lusaka",
    "District": "Lusaka",
    "IsFractionalized": true,
    "IsLocked": true,
    "LockedReason": "Pledged as repo collateral"
  },
  {
    "TokenId": "SCZ-CRB-0016",
    "TokenType": "CorporateBond",
    "Name": "Prime Insurance Corporate Bond 2024-16",
    "Description": "Fixed-rate corporate bond issued by Prime Insurance. Tenor: 7 years. Coupon: 12.0%",
    "OwnerDid": "did:zambia:bank:scz-001",
    "OwnerName": "Standard Chartered Zambia",
    "Status": "Active",
    "Value": 1278756.8,
    "Currency": "ZMW",
    "Quantity": 5657,
    "CreatedAt": "2024-06-26T05:21:22",
    "Province": "Lusaka",
    "District": "Lusaka",
    "IsFractionalized": true,
    "IsLocked": false,
    "LockedReason": null
  },
  {
    "TokenId": "SCZ-EQT-0017",
    "TokenType": "CommonStock",
    "Name": "Copperbelt Energy Corp \u2013 SCZ Equity Custody",
    "Description": "LuSE-listed common stock of Copperbelt Energy Corp in SCZ custodial account. Book-entry settlement.",
    "OwnerDid": "did:zambia:bank:scz-001",
    "OwnerName": "Standard Chartered Zambia",
    "Status": "Active",
    "Value": 10624790.15,
    "Currency": "ZMW",
    "Quantity": 549268,
    "CreatedAt": "2025-05-25T05:21:22",
    "Province": "Lusaka",
    "District": "Lusaka",
    "IsFractionalized": true,
    "IsLocked": false
  },
  {
    "TokenId": "SCZ-EQT-0018",
    "TokenType": "CommonStock",
    "Name": "Zambia Sugar Plc \u2013 SCZ Equity Custody",
    "Description": "LuSE-listed common stock of Zambia Sugar Plc in SCZ custodial account. Book-entry settlement.",
    "OwnerDid": "did:zambia:bank:scz-001",
    "OwnerName": "Standard Chartered Zambia",
    "Status": "Active",
    "Value": 16807150.67,
    "Currency": "ZMW",
    "Quantity": 273202,
    "CreatedAt": "2025-06-10T05:21:22",
    "Province": "Lusaka",
    "District": "Lusaka",
    "IsFractionalized": true,
    "IsLocked": false
  },
  {
    "TokenId": "SCZ-EQT-0019",
    "TokenType": "CommonStock",
    "Name": "Lafarge Zambia \u2013 SCZ Equity Custody",
    "Description": "LuSE-listed common stock of Lafarge Zambia in SCZ custodial account. Book-entry settlement.",
    "OwnerDid": "did:zambia:bank:scz-001",
    "OwnerName": "Standard Chartered Zambia",
    "Status": "Active",
    "Value": 7839497.19,
    "Currency": "ZMW",
    "Quantity": 283082,
    "CreatedAt": "2025-04-18T05:21:22",
    "Province": "Lusaka",
    "District": "Lusaka",
    "IsFractionalized": true,
    "IsLocked": false
  },
  {
    "TokenId": "SCZ-EQT-0020",
    "TokenType": "CommonStock",
    "Name": "National Milling Corp \u2013 SCZ Equity Custody",
    "Description": "LuSE-listed common stock of National Milling Corp in SCZ custodial account. Book-entry settlement.",
    "OwnerDid": "did:zambia:bank:scz-001",
    "OwnerName": "Standard Chartered Zambia",
    "Status": "Active",
    "Value": 18284116.49,
    "Currency": "ZMW",
    "Quantity": 296245,
    "CreatedAt": "2024-05-14T05:21:22",
    "Province": "Lusaka",
    "District": "Lusaka",
    "IsFractionalized": true,
    "IsLocked": false
  },
  {
    "TokenId": "SCZ-EQT-0021",
    "TokenType": "CommonStock",
    "Name": "ZCCM Investments Holdings \u2013 SCZ Equity Custody",
    "Description": "LuSE-listed common stock of ZCCM Investments Holdings in SCZ custodial account. Book-entry settlement.",
    "OwnerDid": "did:zambia:bank:scz-001",
    "OwnerName": "Standard Chartered Zambia",
    "Status": "Active",
    "Value": 17580720.32,
    "Currency": "ZMW",
    "Quantity": 393462,
    "CreatedAt": "2025-05-14T05:21:22",
    "Province": "Lusaka",
    "District": "Lusaka",
    "IsFractionalized": true,
    "IsLocked": false
  },
  {
    "TokenId": "SCZ-ETF-0022",
    "TokenType": "ETF",
    "Name": "SADC Equity ETF \u2013 SCZ Tracking Token",
    "Description": "Exchange-traded fund tracking SADC Equity ETF. Managed by SCZ Investment Management Ltd.",
    "OwnerDid": "did:zambia:bank:scz-001",
    "OwnerName": "Standard Chartered Zambia",
    "Status": "Active",
    "Value": 6994275.69,
    "Currency": "ZMW",
    "Quantity": 45457,
    "CreatedAt": "2025-10-24T05:21:22",
    "Province": "Lusaka",
    "District": "Lusaka",
    "IsFractionalized": true,
    "IsLocked": false
  },
  {
    "TokenId": "SCZ-ETF-0023",
    "TokenType": "ETF",
    "Name": "Africa Infrastructure ETF \u2013 SCZ Tracking Token",
    "Description": "Exchange-traded fund tracking Africa Infrastructure ETF. Managed by SCZ Investment Management Ltd.",
    "OwnerDid": "did:zambia:bank:scz-001",
    "OwnerName": "Standard Chartered Zambia",
    "Status": "Active",
    "Value": 7065525.28,
    "Currency": "ZMW",
    "Quantity": 63495,
    "CreatedAt": "2025-11-15T05:21:22",
    "Province": "Lusaka",
    "District": "Lusaka",
    "IsFractionalized": true,
    "IsLocked": false
  },
  {
    "TokenId": "SCZ-ETF-0024",
    "TokenType": "ETF",
    "Name": "Zambia Blue Chip ETF \u2013 SCZ Tracking Token",
    "Description": "Exchange-traded fund tracking Zambia Blue Chip ETF. Managed by SCZ Investment Management Ltd.",
    "OwnerDid": "did:zambia:bank:scz-001",
    "OwnerName": "Standard Chartered Zambia",
    "Status": "Active",
    "Value": 7492088.19,
    "Currency": "ZMW",
    "Quantity": 126586,
    "CreatedAt": "2025-03-01T05:21:22",
    "Province": "Lusaka",
    "District": "Lusaka",
    "IsFractionalized": true,
    "IsLocked": false
  },
  {
    "TokenId": "SCZ-ETF-0025",
    "TokenType": "ETF",
    "Name": "Copperbelt Mining ETF \u2013 SCZ Tracking Token",
    "Description": "Exchange-traded fund tracking Copperbelt Mining ETF. Managed by SCZ Investment Management Ltd.",
    "OwnerDid": "did:zambia:bank:scz-001",
    "OwnerName": "Standard Chartered Zambia",
    "Status": "Active",
    "Value": 3357525.6,
    "Currency": "ZMW",
    "Quantity": 60321,
    "CreatedAt": "2025-07-01T05:21:22",
    "Province": "Lusaka",
    "District": "Lusaka",
    "IsFractionalized": true,
    "IsLocked": false
  }
]